apio/middleware.py
apio_django/middleware.py
apio_django-1.0.13.dist-info/LICENSE
apio_django-1.0.13.dist-info/METADATA
apio_django-1.0.13.dist-info/WHEEL
apio_django-1.0.13.dist-info/top_level.txt
apio_django-1.0.13.dist-info/RECORD
