Metadata-Version: 2.1
Name: apio-django
Version: 1.0.13
Summary: Application error & performance monitoring
Home-page: https://github.com/apio-monitor/apio_django
Author: Apio Team
Author-email: apio.monitor@gmail.com
License: MIT
Platform: UNKNOWN
Classifier: License :: OSI Approved :: MIT License
Classifier: Programming Language :: Python :: 3.6
Classifier: Programming Language :: Python :: 3.7
Classifier: Programming Language :: Python :: 3.8
Requires-Dist: pathlib
Requires-Dist: requests
